utils_slliu/__init__.py
utils_slliu/my_cmd.py
utils_slliu/utils_slliu.py
utils_slliu-0.0.3.dist-info/METADATA
utils_slliu-0.0.3.dist-info/WHEEL
utils_slliu-0.0.3.dist-info/entry_points.txt
utils_slliu-0.0.3.dist-info/top_level.txt
utils_slliu-0.0.3.dist-info/RECORD
